hierarchical_review_mx/__init__.py
hierarchical_review_mx/heat_map_consistent_altair.py
hierarchical_review_mx/polar_bar_plotly.py
hierarchical_review_mx/transformations.py
hierarchical_review_mx-0.1.1.dist-info/LICENSE
hierarchical_review_mx-0.1.1.dist-info/WHEEL
hierarchical_review_mx-0.1.1.dist-info/METADATA
hierarchical_review_mx-0.1.1.dist-info/RECORD
