Metadata-Version: 2.1
Name: hierarchical_review_mx
Version: 0.1.1
Summary: A template Streamlit app
Home-page: https://github.com/niesfutbol/hierarchical_review_mx
Author: NIES
Author-email: nepo@nies.futbol
Requires-Python: >=3.9
Classifier: License :: OSI Approved :: GNU General Public License v3 or later (GPLv3+)
